{
    "args_time": 16.64937170600001,
    "get_time": 27.17606935500004,
    "large_object_size": 107374182400,
    "large_object_time": 261.679264976,
    "num_args": 10000,
    "num_get_args": 10000,
    "num_queued": 1000000,
    "num_returns": 3000,
    "perf_metrics": [
        {
            "perf_metric_name": "10000_args_time",
            "perf_metric_type": "LATENCY",
            "perf_metric_value": 16.64937170600001
        },
        {
            "perf_metric_name": "3000_returns_time",
            "perf_metric_type": "LATENCY",
            "perf_metric_value": 6.035611493999966
        },
        {
            "perf_metric_name": "10000_get_time",
            "perf_metric_type": "LATENCY",
            "perf_metric_value": 27.17606935500004
        },
        {
            "perf_metric_name": "1000000_queued_time",
            "perf_metric_type": "LATENCY",
            "perf_metric_value": 267.56750421299995
        },
        {
            "perf_metric_name": "107374182400_large_object_time",
            "perf_metric_type": "LATENCY",
            "perf_metric_value": 261.679264976
        }
    ],
    "queued_time": 267.56750421299995,
    "returns_time": 6.035611493999966,
    "success": "1"
}
